<?xml version="1.0" encoding="utf-8" ?>
<diff>
<!-- add. purpose: params.
	<params>
-->
	<!-- <t id="690001">Report Small And Medium Enemies</t>
	<t id="690002">Report Enemy Capital Ships</t> -->
	<add sel="//params">
		<param name="kNPCRParam_isValid" required="false" type="internal" default="@this.isplayerowned" />
		<param name="kNPCRParam_reportEnemies_small" required="false" type="bool" text="{1416318, 690001}" default="
			if  @this.assignedcontrolled.isplayerowned and
			@global.$kNPCR_bridgeCrew_userSettings.$userIsAlertEnemies_comm_xssm
			then true else false" />
		<param name="kNPCRParam_reportEnemies_large" required="false" type="bool" text="{1416318, 690002}" default="
			if  @this.assignedcontrolled.isplayerowned and
			@global.$kNPCR_bridgeCrew_userSettings.$userIsAlertEnemies_comm_lxl
			then true else false" />
		<param name="kNPCRParam_doNotEngage" required="false" default="if $holdfire? then $holdfire else false" type="bool" text="{1416318, 690003}" />
	</add>
<!-- add. purpose: send params to move.generic.
	<run_script name="'order.move.recon'">
-->
	<add sel="//run_script[@name=&quot;'order.move.recon'&quot;]">
		<param name="kNPCRParam_reportEnemies_small" value="@$kNPCRParam_reportEnemies_small"/>
		<param name="kNPCRParam_reportEnemies_large" value="@$kNPCRParam_reportEnemies_large"/>
		<param name="kNPCRParam_doNotEngage" value="@$kNPCRParam_doNotEngage"/>
	</add>
</diff>
